libloop_tool.dylib
loop_tool_py.cpython-38-darwin.so
loop_tool_py-0.0.9.dist-info/LICENSE
loop_tool_py-0.0.9.dist-info/METADATA
loop_tool_py-0.0.9.dist-info/WHEEL
loop_tool_py-0.0.9.dist-info/top_level.txt
loop_tool_py-0.0.9.dist-info/RECORD
