Metadata-Version: 2.1
Name: loop-tool-py
Version: 0.0.9
Summary: A lightweight IR for dense linear algebra
Home-page: UNKNOWN
Author: Bram Wasti
Author-email: bwasti@fb.com
License: UNKNOWN
Platform: UNKNOWN
License-File: LICENSE
